pyroll/tension_spreading_interaction.py
pyroll_tension_spreading_interaction-3.1.0.dist-info/METADATA
pyroll_tension_spreading_interaction-3.1.0.dist-info/WHEEL
pyroll_tension_spreading_interaction-3.1.0.dist-info/licenses/LICENSE
pyroll_tension_spreading_interaction-3.1.0.dist-info/RECORD
